{
    "version": "V2",
    "requestId": "72d7b4ff-a7ad-481f-92a9-f803f584b3bb",
    "timestamp": 1693807424661,
    "images": [
        {
            "uid": "dabc3ca04134438f9352f36925df7791",
            "name": "demo",
            "inferResult": "SUCCESS",
            "message": "SUCCESS",
            "validationResult": {
                "result": "NO_REQUESTED"
            },
            "convertedImageInfo": {
                "width": 1072,
                "height": 296,
                "pageIndex": 0,
                "longImage": false
            },
            "fields": [
                {
                    "valueType": "ALL",
                    "boundingPoly": {
                        "vertices": [
                            {
                                "x": 146.0,
                                "y": 88.0
                            },
                            {
                                "x": 533.0,
                                "y": 98.0
                            },
                            {
                                "x": 530.0,
                                "y": 208.0
                            },
                            {
                                "x": 144.0,
                                "y": 198.0
                            }
                        ]
                    },
                    "inferText": "160허",
                    "inferConfidence": 0.9931,
                    "type": "NORMAL",
                    "lineBreak": false
                },
                {
                    "valueType": "ALL",
                    "boundingPoly": {
                        "vertices": [
                            {
                                "x": 545.0,
                                "y": 96.0
                            },
                            {
                                "x": 923.0,
                                "y": 100.0
                            },
                            {
                                "x": 921.0,
                                "y": 215.0
                            },
                            {
                                "x": 544.0,
                                "y": 211.0
                            }
                        ]
                    },
                    "inferText": "5541",
                    "inferConfidence": 0.9996,
                    "type": "NORMAL",
                    "lineBreak": true
                }
            ]
        }
    ]
}